eye/__init__.py
EyeSim_Python-1.2.4.dist-info/METADATA
EyeSim_Python-1.2.4.dist-info/WHEEL
EyeSim_Python-1.2.4.dist-info/top_level.txt
EyeSim_Python-1.2.4.dist-info/RECORD
